banner_tbongkim03/__init__.py
banner_tbongkim03/banner.py
banner_tbongkim03-0.3.2.dist-info/METADATA
banner_tbongkim03-0.3.2.dist-info/WHEEL
banner_tbongkim03-0.3.2.dist-info/entry_points.txt
banner_tbongkim03-0.3.2.dist-info/top_level.txt
banner_tbongkim03-0.3.2.dist-info/RECORD
