Metadata-Version: 2.1
Name: banner_tbongkim03
Version: 0.3.2
Summary: banner project
Author-email: tbongkim03 <tbongkim03@gmial.com>
License: MIT
Project-URL: HOMEPAGE, https://github.com/tbongkim03/banner_tbongkim03
Project-URL: ISSUES, https://github.com/tbongkim03/banner_tbongkim03/issues
Requires-Python: >=3.9
Requires-Dist: pyfiglet >=1.0.2
